givtrae-0.1.3.data/scripts/mkgtree.py
mkgtree/__init__.py
mkgtree/__main__.py
mkgtree/mkgtree.py
givtrae-0.1.3.dist-info/METADATA
givtrae-0.1.3.dist-info/WHEEL
givtrae-0.1.3.dist-info/entry_points.txt
givtrae-0.1.3.dist-info/top_level.txt
givtrae-0.1.3.dist-info/RECORD
